webhook_command_runner/__init__.py
webhook_command_runner/webserver.py
webhook_command_runner-1.0.4.dist-info/LICENSE
webhook_command_runner-1.0.4.dist-info/METADATA
webhook_command_runner-1.0.4.dist-info/WHEEL
webhook_command_runner-1.0.4.dist-info/entry_points.txt
webhook_command_runner-1.0.4.dist-info/top_level.txt
webhook_command_runner-1.0.4.dist-info/RECORD
