Metadata-Version: 2.1
Name: webhook-command-runner
Version: 1.0.4
Summary: A simple and small webserver to react to webhook-calls by running commands.For simplicity, webhook-urls and scripts are configured in a configfile.
Home-page: https://github.com/autofelge1024/webhook_command_runner
Author: autofelge1024
Author-email: mail@autofelge1024.de
License: MIT
Platform: UNKNOWN
Classifier: Programming Language :: Python :: 3
Classifier: License :: OSI Approved :: MIT License
Classifier: Operating System :: POSIX
Requires-Python: >=3.4
